CHANGELOG.md
LICENSE
unit_testing/__init__.py
unit_testing/date.py
unit_testing-1.0.4.dist-info/LICENSE
unit_testing-1.0.4.dist-info/METADATA
unit_testing-1.0.4.dist-info/WHEEL
unit_testing-1.0.4.dist-info/RECORD
