Metadata-Version: 2.1
Name: unit-testing
Version: 1.0.4
Summary: An example project for showcasing unit testing.
Home-page: https://pypi.org/project/5G00EV17-3001_unit-testing/
License: MIT
Keywords: python3
Author: Lari Liuhamo
Author-email: lari.liuhamo+pypi@gmail.com
Maintainer: Lari Liuhamo
Maintainer-email: lari.liuhamo+pypi@gmail.com
Requires-Python: >=3.11.0,<4.0.0
Classifier: Development Status :: 5 - Production/Stable
Classifier: License :: OSI Approved :: MIT License
Classifier: Operating System :: OS Independent
Classifier: Programming Language :: Python :: 3
Classifier: Programming Language :: Python :: 3.11
Classifier: Programming Language :: Python :: 3.12
Classifier: Programming Language :: Python :: Implementation :: CPython
Classifier: Programming Language :: Python :: Implementation :: PyPy
Classifier: Typing :: Typed
Project-URL: Changelog, https://github.com/Diapolo10/unit_testing/blob/main/CHANGELOG.md
Project-URL: Documentation, https://github.com/Diapolo10/5G00EV17-3001_unit-testing/tree/main/docs
Project-URL: Repository, https://github.com/Diapolo10/5G00EV17-3001_unit-testing
Project-URL: Source code, https://github.com/Diapolo10/unit_testing
Project-URL: Tracker, https://github.com/Diapolo10/unit_testing/issues
